odoo8_addon_sale_order_lot_selection-8.0.1.0.0.99.dev31-py3.8-nspkg.pth
odoo_addons/sale_order_lot_selection/README.rst
odoo_addons/sale_order_lot_selection/__init__.py
odoo_addons/sale_order_lot_selection/__openerp__.py
odoo_addons/sale_order_lot_selection/i18n/ca.po
odoo_addons/sale_order_lot_selection/i18n/de.po
odoo_addons/sale_order_lot_selection/i18n/es.po
odoo_addons/sale_order_lot_selection/i18n/es_AR.po
odoo_addons/sale_order_lot_selection/i18n/es_ES.po
odoo_addons/sale_order_lot_selection/i18n/es_MX.po
odoo_addons/sale_order_lot_selection/i18n/fi.po
odoo_addons/sale_order_lot_selection/i18n/fr.po
odoo_addons/sale_order_lot_selection/i18n/hr.po
odoo_addons/sale_order_lot_selection/i18n/hu.po
odoo_addons/sale_order_lot_selection/i18n/it.po
odoo_addons/sale_order_lot_selection/i18n/nl.po
odoo_addons/sale_order_lot_selection/i18n/nl_NL.po
odoo_addons/sale_order_lot_selection/i18n/pt.po
odoo_addons/sale_order_lot_selection/i18n/pt_BR.po
odoo_addons/sale_order_lot_selection/i18n/pt_PT.po
odoo_addons/sale_order_lot_selection/i18n/ro.po
odoo_addons/sale_order_lot_selection/i18n/sale_order_lot_selection.pot
odoo_addons/sale_order_lot_selection/i18n/sk.po
odoo_addons/sale_order_lot_selection/i18n/sl.po
odoo_addons/sale_order_lot_selection/i18n/tr.po
odoo_addons/sale_order_lot_selection/i18n/tr_TR.po
odoo_addons/sale_order_lot_selection/i18n/zh_CN.po
odoo_addons/sale_order_lot_selection/model/__init__.py
odoo_addons/sale_order_lot_selection/model/procurement.py
odoo_addons/sale_order_lot_selection/model/sale.py
odoo_addons/sale_order_lot_selection/model/stock.py
odoo_addons/sale_order_lot_selection/static/description/icon.png
odoo_addons/sale_order_lot_selection/tests/__init__.py
odoo_addons/sale_order_lot_selection/tests/test_sale_order_lot_selection.py
odoo_addons/sale_order_lot_selection/view/sale_view.xml
odoo8_addon_sale_order_lot_selection-8.0.1.0.0.99.dev31.dist-info/METADATA
odoo8_addon_sale_order_lot_selection-8.0.1.0.0.99.dev31.dist-info/WHEEL
odoo8_addon_sale_order_lot_selection-8.0.1.0.0.99.dev31.dist-info/namespace_packages.txt
odoo8_addon_sale_order_lot_selection-8.0.1.0.0.99.dev31.dist-info/top_level.txt
odoo8_addon_sale_order_lot_selection-8.0.1.0.0.99.dev31.dist-info/RECORD
